rmoq/__init__.py
rmoq/backends.py
rmoq/base.py
rmoq/compat.py
rmoq-0.4.2.dist-info/DESCRIPTION.rst
rmoq-0.4.2.dist-info/METADATA
rmoq-0.4.2.dist-info/RECORD
rmoq-0.4.2.dist-info/WHEEL
rmoq-0.4.2.dist-info/metadata.json
rmoq-0.4.2.dist-info/top_level.txt
