Metadata-Version: 2.0
Name: rmoq
Version: 0.4.2
Summary: A simple request-mocker that will download
Home-page: http://github.com/relekang/rmoq
Author: Rolf Erik Lekang
Author-email: me@rolflekang.com
License: MIT
Platform: UNKNOWN
Classifier: Programming Language :: Python
Classifier: Programming Language :: Python :: 2.7
Classifier: Programming Language :: Python :: 3.4
Requires-Dist: mock (~=1.0.1)
Requires-Dist: requests
Requires-Dist: six (>=1.9.0)
